AUTHORS
CHANGES.rst
COPYING.LGPLv3
MANIFEST.in
README.rst
requirements.txt
setup.py
autoreports/__init__.py
autoreports/adaptors.py
autoreports/admin.py
autoreports/adminfilters.py
autoreports/adminfilters_utils.py
autoreports/api.py
autoreports/csv_to_excel.py
autoreports/fields.py
autoreports/forms.py
autoreports/importlib.py
autoreports/main.py
autoreports/model_forms.py
autoreports/models.py
autoreports/registry.py
autoreports/urls.py
autoreports/utils.py
autoreports/views.py
autoreports/wizards.py
autoreports/locale/en/LC_MESSAGES/django.mo
autoreports/locale/en/LC_MESSAGES/django.po
autoreports/locale/es/LC_MESSAGES/django.mo
autoreports/locale/es/LC_MESSAGES/django.po
autoreports/media/admin_autoreports.css
autoreports/media/using.png
autoreports/media/warning.png
autoreports/media/wizard.css
autoreports/migrations/0001_initial.py
autoreports/migrations/0002_auto__del_field_report_report_filter_fields__del_field_report_advanced.py
autoreports/migrations/__init__.py
autoreports/templates/autoreports/as_wizard_field.html
autoreports/templates/autoreports/autoreports_form.html
autoreports/templates/autoreports/autoreports_list.html
autoreports/templates/autoreports/autoreports_render_instance.html
autoreports/templates/autoreports/autoreports_report_list.html
autoreports/templates/autoreports/autoreports_wizard.html
autoreports/templates/autoreports/inc.medialibraries.html
autoreports/templates/autoreports/inc.render_choices.html
autoreports/templates/autoreports/inc.render_model.html
autoreports/templates/autoreports/admin/autoreports_form.html
autoreports/templates/autoreports/admin/autoreports_tools.html
autoreports/templates/autoreports/admin/autoreports_wizard.html
autoreports/templates/autoreports/admin/report_list.html
autoreports/templates/autoreports/fields/func_field_wizard.html
autoreports/templatetags/__init__.py
autoreports/templatetags/autoreports_tags.py
django_autoreports.egg-info/PKG-INFO
django_autoreports.egg-info/SOURCES.txt
django_autoreports.egg-info/dependency_links.txt
django_autoreports.egg-info/not-zip-safe
django_autoreports.egg-info/requires.txt
django_autoreports.egg-info/top_level.txt
testing/__init__.py
testing/manage.py
testing/settings.py
testing/urls.py
