Metadata-Version: 1.0
Name: django-autoreports
Version: 0.8.6
Summary: Django application that lets you create reports
Home-page: https://github.com/Yaco-Sistemas/django-autoreports
Author: Yaco Sistemas S.L.
Author-email: pmartin@yaco.es
License: LGPL 3
Keywords: django,autoreports,reports,csv,xls,excel,wizard,filters,change list
Platform: UNKNOWN
Classifier: Development Status :: 4 - Beta
Classifier: Framework :: Django
Classifier: License :: OSI Approved :: GNU Library or Lesser General Public License (LGPL)
